[
    {
        "type": "message",
        "user": "U0ASPMFPS",
        "text": "Good morning",
        "ts": "1466765881.000439"
    },
    {
        "type": "message",
        "user": "U07E9GKUZ",
        "text": "morning",
        "ts": "1466766325.000440"
    },
    {
        "type": "message",
        "user": "U07E9GKUZ",
        "text": "leave won, so it goes",
        "ts": "1466766353.000441"
    },
    {
        "type": "message",
        "user": "U040MK408",
        "text": "yeah, sad day for the country",
        "ts": "1466768661.000442"
    },
    {
        "type": "message",
        "user": "U040MK408",
        "text": "anyway",
        "ts": "1466768674.000443"
    },
    {
        "type": "message",
        "user": "U040MK408",
        "text": "don\u2019t panic and carry on",
        "ts": "1466768681.000444"
    },
    {
        "type": "message",
        "user": "U0ASPMFPS",
        "text": "yeah we say that now, until we realise Nigel Farage might end up winning the next General Election",
        "ts": "1466768799.000445"
    },
    {
        "type": "message",
        "user": "U07E9GKUZ",
        "text": "keep doing what I do",
        "ts": "1466769261.000446"
    },
    {
        "type": "message",
        "user": "U07E9GKUZ",
        "text": "which is",
        "ts": "1466769264.000447"
    },
    {
        "type": "message",
        "subtype": "file_share",
        "text": "<@U07E9GKUZ|arkham> uploaded a file: <https:\/\/emberlondon.slack.com\/files\/arkham\/F1L0PR4GN\/programming.gif|programming.gif>",
        "file": {
            "id": "F1L0PR4GN",
            "created": 1466769267,
            "timestamp": 1466769267,
            "name": "programming.gif",
            "title": "programming.gif",
            "mimetype": "image\/gif",
            "filetype": "gif",
            "pretty_type": "GIF",
            "user": "U07E9GKUZ",
            "editable": false,
            "size": 81892,
            "mode": "hosted",
            "is_external": false,
            "external_type": "",
            "is_public": true,
            "public_url_shared": false,
            "display_as_bot": false,
            "username": "",
            "url_private": "https:\/\/files.slack.com\/files-pri\/T03SSL0FF-F1L0PR4GN\/programming.gif?t=xoxe-3910680525-115741181265-116496169492-28d023e02c",
            "url_private_download": "https:\/\/files.slack.com\/files-pri\/T03SSL0FF-F1L0PR4GN\/download\/programming.gif?t=xoxe-3910680525-115741181265-116496169492-28d023e02c",
            "thumb_64": "https:\/\/files.slack.com\/files-tmb\/T03SSL0FF-F1L0PR4GN-6b1047d83c\/programming_64.png?t=xoxe-3910680525-115741181265-116496169492-28d023e02c",
            "thumb_80": "https:\/\/files.slack.com\/files-tmb\/T03SSL0FF-F1L0PR4GN-6b1047d83c\/programming_80.png?t=xoxe-3910680525-115741181265-116496169492-28d023e02c",
            "thumb_360": "https:\/\/files.slack.com\/files-tmb\/T03SSL0FF-F1L0PR4GN-6b1047d83c\/programming_360.png?t=xoxe-3910680525-115741181265-116496169492-28d023e02c",
            "thumb_360_w": 256,
            "thumb_360_h": 256,
            "thumb_160": "https:\/\/files.slack.com\/files-tmb\/T03SSL0FF-F1L0PR4GN-6b1047d83c\/programming_160.png?t=xoxe-3910680525-115741181265-116496169492-28d023e02c",
            "image_exif_rotation": 1,
            "original_w": 256,
            "original_h": 256,
            "permalink": "https:\/\/emberlondon.slack.com\/files\/arkham\/F1L0PR4GN\/programming.gif",
            "permalink_public": "https:\/\/slack-files.com\/T03SSL0FF-F1L0PR4GN-1f5809dbb1",
            "channels": [
                "C03SSL0GP"
            ],
            "groups": [],
            "ims": [],
            "comments_count": 0
        },
        "user": "U07E9GKUZ",
        "upload": true,
        "display_as_bot": false,
        "username": "<@U07E9GKUZ|arkham>",
        "bot_id": null,
        "ts": "1466769268.000448"
    }
]