[
    {
        "type": "message",
        "subtype": "file_share",
        "text": "<@U04BD6KB1|ksnyde> uploaded a file: <https:\/\/emberlondon.slack.com\/files\/ksnyde\/F2M987JAG\/2016-10-10_07-09-04.png|anyone else seen a Travis error like this:>",
        "file": {
            "id": "F2M987JAG",
            "created": 1476079804,
            "timestamp": 1476079804,
            "name": "2016-10-10_07-09-04.png",
            "title": "anyone else seen a Travis error like this:",
            "mimetype": "image\/png",
            "filetype": "png",
            "pretty_type": "PNG",
            "user": "U04BD6KB1",
            "editable": false,
            "size": 68887,
            "mode": "hosted",
            "is_external": false,
            "external_type": "",
            "is_public": true,
            "public_url_shared": false,
            "display_as_bot": false,
            "username": "",
            "url_private": "https:\/\/files.slack.com\/files-pri\/T03SSL0FF-F2M987JAG\/2016-10-10_07-09-04.png?t=xoxe-3910680525-115741181265-116496169492-28d023e02c",
            "url_private_download": "https:\/\/files.slack.com\/files-pri\/T03SSL0FF-F2M987JAG\/download\/2016-10-10_07-09-04.png?t=xoxe-3910680525-115741181265-116496169492-28d023e02c",
            "thumb_64": "https:\/\/files.slack.com\/files-tmb\/T03SSL0FF-F2M987JAG-c3a103eea7\/2016-10-10_07-09-04_64.png?t=xoxe-3910680525-115741181265-116496169492-28d023e02c",
            "thumb_80": "https:\/\/files.slack.com\/files-tmb\/T03SSL0FF-F2M987JAG-c3a103eea7\/2016-10-10_07-09-04_80.png?t=xoxe-3910680525-115741181265-116496169492-28d023e02c",
            "thumb_360": "https:\/\/files.slack.com\/files-tmb\/T03SSL0FF-F2M987JAG-c3a103eea7\/2016-10-10_07-09-04_360.png?t=xoxe-3910680525-115741181265-116496169492-28d023e02c",
            "thumb_360_w": 360,
            "thumb_360_h": 120,
            "thumb_480": "https:\/\/files.slack.com\/files-tmb\/T03SSL0FF-F2M987JAG-c3a103eea7\/2016-10-10_07-09-04_480.png?t=xoxe-3910680525-115741181265-116496169492-28d023e02c",
            "thumb_480_w": 480,
            "thumb_480_h": 160,
            "thumb_160": "https:\/\/files.slack.com\/files-tmb\/T03SSL0FF-F2M987JAG-c3a103eea7\/2016-10-10_07-09-04_160.png?t=xoxe-3910680525-115741181265-116496169492-28d023e02c",
            "thumb_720": "https:\/\/files.slack.com\/files-tmb\/T03SSL0FF-F2M987JAG-c3a103eea7\/2016-10-10_07-09-04_720.png?t=xoxe-3910680525-115741181265-116496169492-28d023e02c",
            "thumb_720_w": 720,
            "thumb_720_h": 239,
            "image_exif_rotation": 1,
            "original_w": 794,
            "original_h": 264,
            "permalink": "https:\/\/emberlondon.slack.com\/files\/ksnyde\/F2M987JAG\/2016-10-10_07-09-04.png",
            "permalink_public": "https:\/\/slack-files.com\/T03SSL0FF-F2M987JAG-58bf55c80e",
            "channels": [
                "C03SSL0GP"
            ],
            "groups": [],
            "ims": [],
            "comments_count": 0
        },
        "user": "U04BD6KB1",
        "upload": true,
        "display_as_bot": false,
        "username": "<@U04BD6KB1|ksnyde>",
        "bot_id": null,
        "ts": "1476079806.001117"
    },
    {
        "type": "message",
        "subtype": "file_share",
        "text": "<@U04BD6KB1|ksnyde> uploaded a file: <https:\/\/emberlondon.slack.com\/files\/ksnyde\/F2M9CMA9L\/2016-10-10_07-09-20.png|2016-10-10_07-09-20.png> and commented: i'm getting this only for the \"default\" release of ember-try:",
        "file": {
            "id": "F2M9CMA9L",
            "created": 1476079846,
            "timestamp": 1476079846,
            "name": "2016-10-10_07-09-20.png",
            "title": "2016-10-10_07-09-20.png",
            "mimetype": "image\/png",
            "filetype": "png",
            "pretty_type": "PNG",
            "user": "U04BD6KB1",
            "editable": false,
            "size": 38203,
            "mode": "hosted",
            "is_external": false,
            "external_type": "",
            "is_public": true,
            "public_url_shared": false,
            "display_as_bot": false,
            "username": "",
            "url_private": "https:\/\/files.slack.com\/files-pri\/T03SSL0FF-F2M9CMA9L\/2016-10-10_07-09-20.png?t=xoxe-3910680525-115741181265-116496169492-28d023e02c",
            "url_private_download": "https:\/\/files.slack.com\/files-pri\/T03SSL0FF-F2M9CMA9L\/download\/2016-10-10_07-09-20.png?t=xoxe-3910680525-115741181265-116496169492-28d023e02c",
            "thumb_64": "https:\/\/files.slack.com\/files-tmb\/T03SSL0FF-F2M9CMA9L-6822e248a3\/2016-10-10_07-09-20_64.png?t=xoxe-3910680525-115741181265-116496169492-28d023e02c",
            "thumb_80": "https:\/\/files.slack.com\/files-tmb\/T03SSL0FF-F2M9CMA9L-6822e248a3\/2016-10-10_07-09-20_80.png?t=xoxe-3910680525-115741181265-116496169492-28d023e02c",
            "thumb_360": "https:\/\/files.slack.com\/files-tmb\/T03SSL0FF-F2M9CMA9L-6822e248a3\/2016-10-10_07-09-20_360.png?t=xoxe-3910680525-115741181265-116496169492-28d023e02c",
            "thumb_360_w": 360,
            "thumb_360_h": 104,
            "thumb_480": "https:\/\/files.slack.com\/files-tmb\/T03SSL0FF-F2M9CMA9L-6822e248a3\/2016-10-10_07-09-20_480.png?t=xoxe-3910680525-115741181265-116496169492-28d023e02c",
            "thumb_480_w": 480,
            "thumb_480_h": 139,
            "thumb_160": "https:\/\/files.slack.com\/files-tmb\/T03SSL0FF-F2M9CMA9L-6822e248a3\/2016-10-10_07-09-20_160.png?t=xoxe-3910680525-115741181265-116496169492-28d023e02c",
            "thumb_720": "https:\/\/files.slack.com\/files-tmb\/T03SSL0FF-F2M9CMA9L-6822e248a3\/2016-10-10_07-09-20_720.png?t=xoxe-3910680525-115741181265-116496169492-28d023e02c",
            "thumb_720_w": 720,
            "thumb_720_h": 208,
            "thumb_960": "https:\/\/files.slack.com\/files-tmb\/T03SSL0FF-F2M9CMA9L-6822e248a3\/2016-10-10_07-09-20_960.png?t=xoxe-3910680525-115741181265-116496169492-28d023e02c",
            "thumb_960_w": 960,
            "thumb_960_h": 278,
            "image_exif_rotation": 1,
            "original_w": 964,
            "original_h": 279,
            "permalink": "https:\/\/emberlondon.slack.com\/files\/ksnyde\/F2M9CMA9L\/2016-10-10_07-09-20.png",
            "permalink_public": "https:\/\/slack-files.com\/T03SSL0FF-F2M9CMA9L-5e2a87029f",
            "channels": [
                "C03SSL0GP"
            ],
            "groups": [],
            "ims": [],
            "comments_count": 1,
            "initial_comment": {
                "id": "Fc2M9C1Y9W",
                "created": 1476079846,
                "timestamp": 1476079846,
                "user": "U04BD6KB1",
                "is_intro": true,
                "comment": "i'm getting this only for the \"default\" release of ember-try:",
                "channel": ""
            }
        },
        "user": "U04BD6KB1",
        "upload": true,
        "display_as_bot": false,
        "username": "<@U04BD6KB1|ksnyde>",
        "bot_id": null,
        "ts": "1476079848.001118"
    },
    {
        "type": "message",
        "user": "U04BD6KB1",
        "text": "nevermind ... second cup of coffee solved this problem",
        "ts": "1476079906.001119"
    },
    {
        "type": "message",
        "user": "U04BD6KB1",
        "text": "this channel has gotten rather quite recently ... hope everyone is well",
        "ts": "1476079928.001120",
        "reactions": [
            {
                "name": "+1",
                "users": [
                    "U0A48LWTG"
                ],
                "count": 1
            }
        ]
    }
]