[
    {
        "type": "message",
        "user": "U047GTU64",
        "text": "<@U043951H9> bugsnag?",
        "ts": "1476795370.001480"
    },
    {
        "type": "message",
        "user": "U047GTU64",
        "text": "or you mean this <https:\/\/chrome.google.com\/webstore\/detail\/bugsnap\/mfodpdfcbkmkdebahlkghnegochneenh> ?",
        "attachments": [
            {
                "title": "BugSnap",
                "title_link": "https:\/\/chrome.google.com\/webstore\/detail\/bugsnap\/mfodpdfcbkmkdebahlkghnegochneenh",
                "text": "Shoot your bug and send photo to your tracker.",
                "fallback": "BugSnap",
                "from_url": "https:\/\/chrome.google.com\/webstore\/detail\/bugsnap\/mfodpdfcbkmkdebahlkghnegochneenh",
                "thumb_url": "https:\/\/lh3.googleusercontent.com\/z1BDglycU4k8tdxjQQYne-HZbE2NTpOVIZXCPPucTCG8ZKDbvpRfnmeFRA88CW_kN-pX-4ZcXQ",
                "thumb_width": 128,
                "thumb_height": 128,
                "service_icon": "https:\/\/www.google.com\/images\/icons\/product\/chrome_web_store-32.png",
                "service_name": "chrome.google.com",
                "id": 1
            }
        ],
        "ts": "1476795409.001481"
    },
    {
        "type": "message",
        "user": "U047GTU64",
        "text": "lol these names though",
        "ts": "1476795415.001483"
    },
    {
        "type": "message",
        "user": "U1XB7HR3J",
        "text": "has anyone tweaked their ember-cli-build.js file to produce 1:1 output for transpiled JS files for a development build rather that the many:1 default that produces vendor.js and app.js? - I appreciate that sourcemaps exist but was wondering if there was another path",
        "edited": {
            "user": "U1XB7HR3J",
            "ts": "1476806770.000000"
        },
        "ts": "1476806064.001484"
    },
    {
        "type": "message",
        "user": "U043951H9",
        "text": "<@U047GTU64>: bugsnag the exception tool",
        "ts": "1476807683.001486"
    },
    {
        "type": "message",
        "user": "U04BGLGM3",
        "text": "Does anyone know any good blog posts, articles or tips to deal with nested models that related to each other on one route. I.e.\n`foo`, `bar`, `baz`. A `foo` has many `bar` and each `bar` has many `baz`. So when you load a `foo` you want your url to be `\/foo\/1` but you want it to show every `bar` and all the `baz` for each. It feels like the `foo` route starts to become a God route, I started using an `RSVP.hash` that resolves the `foo` and then all the `bar` for that `foo`\u2026 and then all the `baz` for each `bar`? (I\u2019ve not tried loading the `baz`on the `foo` route).\n\nDoes that even make sense? I can change `foo` `bar` and `baz` to something real world like `document`, `section`, `task` if that helps :stuck_out_tongue_winking_eye:\u2026\n\nThis kinda touches on it, and might be a solution: <http:\/\/forspareparts.github.io\/2016\/01\/24\/actions-up-data-sideways\/>",
        "attachments": [
            {
                "title": "Actions Up, Data Sideways",
                "title_link": "http:\/\/forspareparts.github.io\/2016\/01\/24\/actions-up-data-sideways\/",
                "text": "The rallying cry for Ember 2.0 has been \u201cData Down, Actions Up,\u201d indicating apattern wherein parents (routes\/controllers, or high-level components) passdat...",
                "fallback": "Actions Up, Data Sideways",
                "from_url": "http:\/\/forspareparts.github.io\/2016\/01\/24\/actions-up-data-sideways\/",
                "service_name": "forspareparts.github.io",
                "id": 1
            }
        ],
        "ts": "1476808385.001487"
    },
    {
        "type": "message",
        "user": "U04BD6KB1",
        "text": "is it true that Ember 2.9.0 didn't ship with Glimmer 2?",
        "ts": "1476818907.001489"
    },
    {
        "type": "message",
        "user": "U04BD6KB1",
        "text": "just noticed this in travis:",
        "ts": "1476818940.001490"
    },
    {
        "type": "message",
        "subtype": "file_share",
        "text": "<@U04BD6KB1|ksnyde> uploaded a file: <https:\/\/emberlondon.slack.com\/files\/ksnyde\/F2R15Q5NW\/pasted_image_at_2016_10_18_08_29_pm.png|Pasted image at 2016-10-18, 8:29 PM>",
        "file": {
            "id": "F2R15Q5NW",
            "created": 1476818942,
            "timestamp": 1476818942,
            "name": "Pasted image at 2016_10_18 08_29 PM.png",
            "title": "Pasted image at 2016-10-18, 8:29 PM",
            "mimetype": "image\/png",
            "filetype": "png",
            "pretty_type": "PNG",
            "user": "U04BD6KB1",
            "editable": false,
            "size": 14121,
            "mode": "hosted",
            "is_external": false,
            "external_type": "",
            "is_public": true,
            "public_url_shared": false,
            "display_as_bot": false,
            "username": "",
            "url_private": "https:\/\/files.slack.com\/files-pri\/T03SSL0FF-F2R15Q5NW\/pasted_image_at_2016_10_18_08_29_pm.png?t=xoxe-3910680525-115741181265-116496169492-28d023e02c",
            "url_private_download": "https:\/\/files.slack.com\/files-pri\/T03SSL0FF-F2R15Q5NW\/download\/pasted_image_at_2016_10_18_08_29_pm.png?t=xoxe-3910680525-115741181265-116496169492-28d023e02c",
            "thumb_64": "https:\/\/files.slack.com\/files-tmb\/T03SSL0FF-F2R15Q5NW-913c424533\/pasted_image_at_2016_10_18_08_29_pm_64.png?t=xoxe-3910680525-115741181265-116496169492-28d023e02c",
            "thumb_80": "https:\/\/files.slack.com\/files-tmb\/T03SSL0FF-F2R15Q5NW-913c424533\/pasted_image_at_2016_10_18_08_29_pm_80.png?t=xoxe-3910680525-115741181265-116496169492-28d023e02c",
            "thumb_360": "https:\/\/files.slack.com\/files-tmb\/T03SSL0FF-F2R15Q5NW-913c424533\/pasted_image_at_2016_10_18_08_29_pm_360.png?t=xoxe-3910680525-115741181265-116496169492-28d023e02c",
            "thumb_360_w": 360,
            "thumb_360_h": 40,
            "thumb_480": "https:\/\/files.slack.com\/files-tmb\/T03SSL0FF-F2R15Q5NW-913c424533\/pasted_image_at_2016_10_18_08_29_pm_480.png?t=xoxe-3910680525-115741181265-116496169492-28d023e02c",
            "thumb_480_w": 480,
            "thumb_480_h": 53,
            "thumb_160": "https:\/\/files.slack.com\/files-tmb\/T03SSL0FF-F2R15Q5NW-913c424533\/pasted_image_at_2016_10_18_08_29_pm_160.png?t=xoxe-3910680525-115741181265-116496169492-28d023e02c",
            "thumb_720": "https:\/\/files.slack.com\/files-tmb\/T03SSL0FF-F2R15Q5NW-913c424533\/pasted_image_at_2016_10_18_08_29_pm_720.png?t=xoxe-3910680525-115741181265-116496169492-28d023e02c",
            "thumb_720_w": 720,
            "thumb_720_h": 79,
            "image_exif_rotation": 1,
            "original_w": 864,
            "original_h": 95,
            "permalink": "https:\/\/emberlondon.slack.com\/files\/ksnyde\/F2R15Q5NW\/pasted_image_at_2016_10_18_08_29_pm.png",
            "permalink_public": "https:\/\/slack-files.com\/T03SSL0FF-F2R15Q5NW-619e9413a6",
            "channels": [
                "C03SSL0GP"
            ],
            "groups": [],
            "ims": [],
            "comments_count": 0
        },
        "user": "U04BD6KB1",
        "upload": true,
        "display_as_bot": false,
        "username": "<@U04BD6KB1|ksnyde>",
        "bot_id": null,
        "ts": "1476818944.001491"
    },
    {
        "type": "message",
        "user": "U04BD6KB1",
        "text": "guess it didn't: <http:\/\/emberjs.com\/blog\/2016\/10\/17\/ember-2-9-released.html>",
        "attachments": [
            {
                "title": "Ember.js: Ember.js 2.8-LTS, 2.9 and 2.10 Beta Released",
                "title_link": "http:\/\/emberjs.com\/blog\/2016\/10\/17\/ember-2-9-released.html",
                "text": "Ember.js helps developers be more productive out of the box. Designed with developer ergonomics in mind, its friendly APIs help you get your job done\u2014fast.",
                "fallback": "Ember.js: Ember.js 2.8-LTS, 2.9 and 2.10 Beta Released",
                "thumb_url": "http:\/\/emberjs.com\/images\/tomster-sm.png",
                "from_url": "http:\/\/emberjs.com\/blog\/2016\/10\/17\/ember-2-9-released.html",
                "thumb_width": 220,
                "thumb_height": 220,
                "service_icon": "http:\/\/emberjs.com\/images\/favicon.png",
                "service_name": "emberjs.com",
                "id": 1
            }
        ],
        "ts": "1476819314.001492"
    },
    {
        "type": "message",
        "user": "U043AB2QT",
        "text": "Glad we have such a great beta community that are willing to test this sort of thing to ensure they ship quality. ",
        "ts": "1476819610.001494"
    },
    {
        "type": "message",
        "user": "U04BD6KB1",
        "text": "yeah i guess that's a good point",
        "ts": "1476819643.001495"
    }
]